[
  {
    "uid": 4641833615,
    "password": "S_WMGI4_BY_STAR_GMR_W9L05",
    "account_id": "15068175915",
    "name": "SG_LIKE¹¹⁹¹²",
    "region": "BD",
    "date_created": "2026-03-15 10:05:52",
    "thread_id": 4
  },
    {
    "uid": 4561759163,
    "password": "FAST_PZG7W_BY_STAR_GMR_TTTTA",
    "account_id": "16347146118",
    "name": "STAR_⁸⁷⁷¹",
    "region": "IND",
    "date_created": "2026-07-09 12:54:03",
    "thread_id": 1
  },
  {
    "uid": 5523319335,
    "password": "STARR_BYSTARGMR_bC1hULKj",
    "account_id": "16347295009",
    "name": "STAR__⁵⁵⁵⁶",
    "region": "ME",
    "date_created": "2026-07-09 13:11:03",
    "thread_id": 12
  },
    {
    "uid": "4653877652",
    "password": "4WFP9PH1QWGEJUN17UAIL82KAV279Y6ZG6UMTWWO65SX0EN85TIQPPNAJADPD4WX",
    "account_id": "15127934735",
    "name": "KNT⁷³²⁷⁴⁶¹³⁴",
    "region": "BR",
    "Level": 4,
    "date_created": "2026-07-12 06:42:37"
  }
]
  
